microblog/__init__.py
microblog/cli.py
microblog/images.py
microblog/input.py
microblog/logging.py
microblog/pelican.py
microblog/renderers.py
microblog/storage.py
microblog/yaml.py
microblog_server-1.0.2.dist-info/LICENSE
microblog_server-1.0.2.dist-info/METADATA
microblog_server-1.0.2.dist-info/WHEEL
microblog_server-1.0.2.dist-info/entry_points.txt
microblog_server-1.0.2.dist-info/top_level.txt
microblog_server-1.0.2.dist-info/RECORD
